AUTHORS
ChangeLog
LICENSE.txt
README.md
requirements.txt
setup.cfg
setup.py
desolvex/__init__.py
desolvex.egg-info/PKG-INFO
desolvex.egg-info/SOURCES.txt
desolvex.egg-info/dependency_links.txt
desolvex.egg-info/not-zip-safe
desolvex.egg-info/pbr.json
desolvex.egg-info/requires.txt
desolvex.egg-info/top_level.txt
desolvex/ade/__init__.py
desolvex/ade/ade.py
desolvex/domain/.DS_Store
desolvex/domain/__init__.py
desolvex/domain/cartesian.py
desolvex/domain/domain.py
desolvex/domain/rectilinear.py
desolvex/helper/__init__.py
desolvex/helper/objectswapper.py
desolvex/probe/__init__.py
desolvex/probe/sink.py
desolvex/solver/__init__.py
desolvex/solver/explicitsolver.py
desolvex/source/__init__.py
desolvex/source/functions.py
desolvex/source/source.py
desolvex/stopcriteria/__init__.py
desolvex/stopcriteria/iterationstopcriterium.py
examples/wave_equation.py