Metadata-Version: 1.1
Name: desolvex
Version: 17.5.8.dev1
Summary: Framework for the solution of partial differential equations
Home-page: https://github.com/cstatz/desolvex
Author: Christoph Statz
Author-email: christoph.statz@tu-dresden.de
License: BSD-3-Clause
Platform: UNKNOWN
Classifier: Development Status :: 3 - Alpha
Classifier: Environment :: Console
Classifier: Intended Audience :: Developers
Classifier: Intended Audience :: Science/Research
Classifier: License :: OSI Approved :: BSD License
Classifier: Operating System :: OS Independent
Classifier: Programming Language :: Python
Classifier: Topic :: Scientific/Engineering :: Mathematics
Classifier: Topic :: Scientific/Engineering :: Physics
Classifier: Natural Language :: English
